mpinum/__init__.py
mpinum/pnCubeDecomp.py
mpinum/pnDistArray.py
mpinum/pnDomainPartitionIter.py
mpinum/pnGhostedDistArray.py
mpinum/pnLaplacian.py
mpinum/pnMultiArrayIter.py
mpinum/pnPartition.py
mpinum/pnStencilOperator.py
mpinum-1.4.3.dist-info/LICENSE
mpinum-1.4.3.dist-info/METADATA
mpinum-1.4.3.dist-info/WHEEL
mpinum-1.4.3.dist-info/top_level.txt
mpinum-1.4.3.dist-info/RECORD
