Metadata-Version: 2.1
Name: mpinum
Version: 1.4.3
Summary: A very lightweight implementation of distributed arrays
Home-page: https://github.com/pletzer/mpinum.git
Author: Alexander Pletzer
Author-email: alexander@gokliya.net
License-File: LICENSE
Requires-Dist: numpy
Requires-Dist: mpi4py
